{
  "height": "3000",
  "width": "5120",
  "objects": [
    {
      "type": "road_2lane_straight",
      "x": 0,
      "y": 0,
      "m11": 1.0,
      "m12": 0.0,
      "m21": 0.0,
      "m22": 0.1
    },
    {
      "type": "garage",
      "x": 600,
      "y": 0,
      "m11": 1.0,
      "m12": 0.0,
      "m21": 0.0,
      "m22": 0.1
    },
    {
      "type": "tree",
      "x": 600,
      "y": 300,
      "m11": 1.0,
      "m12": 0.0,
      "m21": 0.0,
      "m22": 0.1
    },
    {
      "type": "roadsign_parking_right",
      "x": 800,
      "y": 300,
      "m11": 1.0,
      "m12": 0.0,
      "m21": 0.0,
      "m22": 0.1
    },
    {
      "type": "roadsign_priority_stop",
      "x": 800,
      "y": 400,
      "m11": 1.0,
      "m12": 0.0,
      "m21": 0.0,
      "m22": 0.1
    },
    {
      "type": "roadsign_speed_40",
      "x": 900,
      "y": 300,
      "m11": 1.0,
      "m12": 0.0,
      "m21": 0.0,
      "m22": 0.1
    },
    {
      "type": "roadsign_speed_50",
      "x": 900,
      "y": 400,
      "m11": 1.0,
      "m12": 0.0,
      "m21": 0.0,
      "m22": 0.1
    },
    {
      "type": "roadsign_speed_60",
      "x": 900,
      "y": 500,
      "m11": 1.0,
      "m12": 0.0,
      "m21": 0.0,
      "m22": 0.1
    },
    {
      "type": "bollard",
      "x": 1000,
      "y": 300,
      "m11": 1.0,
      "m12": 0.0,
      "m21": 0.0,
      "m22": 0.1
    },
    {
      "type": "boundary",
      "x": 1000,
      "y": 400,
      "m11": 1.0,
      "m12": 0.0,
      "m21": 0.0,
      "m22": 0.1
    },
   {
      "type": "man",
      "x": 1000,
      "y": 500,
      "m11": 1.0,
      "m12": 0.0,
      "m21": 0.0,
      "m22": 0.1
    },
    {
      "type": "woman",
      "x": 1050,
      "y": 500,
      "m11": 1.0,
      "m12": 0.0,
      "m21": 0.0,
      "m22": 0.1
    },
    {
      "type": "bicycle",
      "x": 1100,
      "y": 300,
      "m11": 1.0,
      "m12": 0.0,
      "m21": 0.0,
      "m22": 0.1
    },
    {
      "type": "car_1_white",
      "x": 1300,
      "y": 100,
      "m11": 0.0,
      "m12": -1.0,
      "m21": 1.0,
      "m22": 0.0
    },
    {
      "type": "car_1_blue",
      "x": 1300,
      "y": 300,
      "m11": 0.0,
      "m12": -1.0,
      "m21": 1.0,
      "m22": 0.0
    },
    {
      "type": "car_1_red",
      "x": 1300,
      "y": 500,
      "m11": 0.0,
      "m12": -1.0,
      "m21": 1.0,
      "m22": 0.0
    },
    {
      "type": "car_3_black",
      "x": 1300,
      "y": 700,
      "m11": 0.0,
      "m12": -1.0,
      "m21": 1.0,
      "m22": 0.0
    }
  ]
}